mis_utils_con_init/__init__.py
mis_utils_con_init/operaciones.py
mis_utils_con_init/traducciones.py
mis_utils_con_init/validaciones.py
misutils-1.0.1.dist-info/METADATA
misutils-1.0.1.dist-info/WHEEL
misutils-1.0.1.dist-info/top_level.txt
misutils-1.0.1.dist-info/RECORD
