Metadata-Version: 2.1
Name: misutils
Version: 1.0.1
Summary: Paquete con utilidades básicas de operaciones, validaciones y traducciones
Author: Charly Falco
Author-email: c_falco@gmail.com
